LICENSE
MANIFEST.in
README.rst
setup.cfg
setup.py
versioneer.py
artellapipe/__init__.py
artellapipe/tools/__init__.py
artellapipe/tools/bugtracker/__init__.py
artellapipe/tools/bugtracker/__logging__.ini
artellapipe/tools/bugtracker/__version__.py
artellapipe/tools/bugtracker/_version.py
artellapipe/tools/bugtracker/core/__init__.py
artellapipe/tools/bugtracker/core/bugtracker.py
artellapipe/tools/bugtracker/resources/images/bugtracker_logo.png
artellapipe/tools/bugtracker/widgets/__init__.py
artellapipe/tools/bugtracker/widgets/bugtracker.py
artellapipe_tools_bugtracker.egg-info/PKG-INFO
artellapipe_tools_bugtracker.egg-info/SOURCES.txt
artellapipe_tools_bugtracker.egg-info/dependency_links.txt
artellapipe_tools_bugtracker.egg-info/not-zip-safe
artellapipe_tools_bugtracker.egg-info/requires.txt
artellapipe_tools_bugtracker.egg-info/top_level.txt
tests/__init__.py
tests/test_general.py